Metadata-Version: 2.1
Name: topsis-tarndeep-singh-102117210
Version: 1.0
Summary: A package for performing TOPSIS analysis
Author: TARNDEEP SINGH
Author-email: <tsingh3_be21@thapar.edu>
Keywords: python,topsis
Classifier: Programming Language :: Python :: 3
Classifier: License :: OSI Approved :: MIT License
Classifier: Operating System :: OS Independent
License-File: LICENSE.txt
